MESA_Plotter/__init__.py
MESA_Plotter/__main__.py
MESA_Plotter/__version__.py
MESA_Plotter/_MESA_Plotter/MESAPlotter.py
MESA_Plotter/_MESA_Plotter/MESA_Plotter.py
MESA_Plotter/_MESA_Plotter/__init__.py
MESA_Plotter-1.15.dist-info/LICENSE
MESA_Plotter-1.15.dist-info/METADATA
MESA_Plotter-1.15.dist-info/WHEEL
MESA_Plotter-1.15.dist-info/entry_points.txt
MESA_Plotter-1.15.dist-info/top_level.txt
MESA_Plotter-1.15.dist-info/RECORD
