Metadata-Version: 2.1
Name: MESA-Plotter
Version: 1.15
Summary: Plot the evolution of pre-main sequence stars in various way. A tool for the asteroseismology group of the university of Innsbruck, Austria.
Home-page: https://github.com/Steinerkadabra/MESA_Plotter
Author: Thomas Steindl
Author-email: thomas.steindl@uibk.ac.at
License: UNKNOWN
Platform: UNKNOWN
Classifier: Programming Language :: Python :: 3.6
Classifier: License :: OSI Approved :: MIT License
Classifier: Operating System :: OS Independent
Requires-Dist: numpy
Requires-Dist: matplotlib
Requires-Dist: scipy
Requires-Dist: argparse
Requires-Dist: setuptools
